{
  "account": "PS5673",
  "timestamp": "2026-06-05 09:47:23 IST",
  "bot_running": true,
  "total_value": 9449791.15,
  "today_pnl": -102.52,
  "today_pnl_pct": -0.0,
  "liquidcase": {
    "quantity": 79151,
    "price": 114.41,
    "value": 9055665.91,
    "pct": 95.83
  },
  "slots": {
    "total": 5,
    "used": 5,
    "available": 0,
    "active_etfs": [
      "MON100",
      "GOLDBEES",
      "SILVERBEES",
      "JUNIORBEES",
      "MINDSPACE-RR",
      "EMBASSY-RR",
      "BANKBEES"
    ],
    "bnh_symbols": [
      "MID150BEES"
    ],
    "bnh_held": 1
  },
  "holdings": [
    {
      "symbol": "BANKBEES",
      "quantity": 34,
      "avg": 550.41,
      "ltp": 563.25,
      "value": 19150.5,
      "pnl": 67.32,
      "pnl_pct": 0.35,
      "strategy": "active"
    },
    {
      "symbol": "GOLDBEES",
      "quantity": 547,
      "avg": 127.75,
      "ltp": 127.9,
      "value": 69961.3,
      "pnl": -328.2,
      "pnl_pct": -0.47,
      "strategy": "active"
    },
    {
      "symbol": "JUNIORBEES",
      "quantity": 26,
      "avg": 748.0,
      "ltp": 759.53,
      "value": 19747.78,
      "pnl": 89.7,
      "pnl_pct": 0.46,
      "strategy": "active"
    },
    {
      "symbol": "MID150BEES",
      "quantity": 721,
      "avg": 227.48,
      "ltp": 231.78,
      "value": 167113.38,
      "pnl": 872.41,
      "pnl_pct": 0.52,
      "strategy": "bnh"
    },
    {
      "symbol": "MINDSPACE-RR",
      "quantity": 43,
      "avg": 458.0,
      "ltp": 459.88,
      "value": 19774.84,
      "pnl": -64.07,
      "pnl_pct": -0.32,
      "strategy": "active"
    },
    {
      "symbol": "SILVERBEES",
      "quantity": 402,
      "avg": 247.46,
      "ltp": 244.72,
      "value": 98377.44,
      "pnl": -739.68,
      "pnl_pct": -0.75,
      "strategy": "active"
    }
  ],
  "williams_r": [
    {
      "symbol": "MON100",
      "ltp": 342.55,
      "change_pct": 0.17,
      "williams_r": 0.0,
      "is_held": false,
      "avg_price": null,
      "strategy": "active"
    },
    {
      "symbol": "GOLDBEES",
      "ltp": 127.9,
      "change_pct": -0.47,
      "williams_r": -81.67,
      "is_held": true,
      "avg_price": 127.75,
      "strategy": "active"
    },
    {
      "symbol": "SILVERBEES",
      "ltp": 244.72,
      "change_pct": -0.75,
      "williams_r": -96.05,
      "is_held": true,
      "avg_price": 247.45,
      "strategy": "active"
    },
    {
      "symbol": "JUNIORBEES",
      "ltp": 759.53,
      "change_pct": 0.46,
      "williams_r": -40.89,
      "is_held": true,
      "avg_price": 748.0,
      "strategy": "active"
    },
    {
      "symbol": "MINDSPACE-RR",
      "ltp": 459.88,
      "change_pct": -0.32,
      "williams_r": -69.44,
      "is_held": true,
      "avg_price": 458.0,
      "strategy": "active"
    },
    {
      "symbol": "EMBASSY-RR",
      "ltp": 429.67,
      "change_pct": 0.28,
      "williams_r": -45.68,
      "is_held": false,
      "avg_price": null,
      "strategy": "active"
    },
    {
      "symbol": "BANKBEES",
      "ltp": 563.25,
      "change_pct": 0.35,
      "williams_r": -38.3,
      "is_held": true,
      "avg_price": 550.41,
      "strategy": "active"
    },
    {
      "symbol": "MID150BEES",
      "ltp": 231.78,
      "change_pct": 0.52,
      "williams_r": -48.25,
      "is_held": true,
      "avg_price": 227.48,
      "strategy": "bnh"
    }
  ],
  "signals": [],
  "orders": [],
  "available_cash": null,
  "available_margin": null
}