{
  "account": "PS5673",
  "timestamp": "2026-06-09 11:46:55 IST",
  "bot_running": true,
  "total_value": 9340630.59,
  "today_pnl": 7423.94,
  "today_pnl_pct": 0.08,
  "liquidcase": {
    "quantity": 75913,
    "free_quantity": 8595,
    "price": 114.45,
    "value": 8688242.85,
    "pct": 93.02
  },
  "slots": {
    "total": 5,
    "used": 6,
    "available": 0,
    "active_etfs": [
      "GOLDBEES",
      "SILVERBEES",
      "JUNIORBEES",
      "MINDSPACE-RR",
      "EMBASSY-RR",
      "BANKBEES"
    ],
    "bnh_symbols": [
      "MID150BEES"
    ],
    "bnh_held": 1
  },
  "holdings": [
    {
      "symbol": "BANKBEES",
      "quantity": 34,
      "avg": 550.41,
      "ltp": 564.4,
      "value": 19189.6,
      "pnl": 193.46,
      "pnl_pct": 1.02,
      "strategy": "active",
      "buys_today": 0,
      "max_slots": 5
    },
    {
      "symbol": "EMBASSY-RR",
      "quantity": 70,
      "avg": 426.36,
      "ltp": 429.54,
      "value": 30067.8,
      "pnl": 240.1,
      "pnl_pct": 0.8,
      "strategy": "active",
      "buys_today": 0,
      "max_slots": 5
    },
    {
      "symbol": "GOLDBEES",
      "quantity": 1111,
      "avg": 126.14,
      "ltp": 125.88,
      "value": 139852.68,
      "pnl": 1910.92,
      "pnl_pct": 1.39,
      "strategy": "active",
      "buys_today": 0,
      "max_slots": 5
    },
    {
      "symbol": "JUNIORBEES",
      "quantity": 26,
      "avg": 748.0,
      "ltp": 752.0,
      "value": 19552.0,
      "pnl": 185.12,
      "pnl_pct": 0.96,
      "strategy": "active",
      "buys_today": 0,
      "max_slots": 5
    },
    {
      "symbol": "MID150BEES",
      "quantity": 1355,
      "avg": 227.65,
      "ltp": 228.5,
      "value": 309617.5,
      "pnl": 2249.3,
      "pnl_pct": 0.73,
      "strategy": "bnh",
      "buys_today": null,
      "max_slots": 5
    },
    {
      "symbol": "MINDSPACE-RR",
      "quantity": 43,
      "avg": 458.0,
      "ltp": 464.02,
      "value": 19952.86,
      "pnl": 175.44,
      "pnl_pct": 0.89,
      "strategy": "active",
      "buys_today": 0,
      "max_slots": 5
    },
    {
      "symbol": "SILVERBEES",
      "quantity": 490,
      "avg": 244.4,
      "ltp": 232.97,
      "value": 114155.3,
      "pnl": 2469.6,
      "pnl_pct": 2.21,
      "strategy": "active",
      "buys_today": 0,
      "max_slots": 5
    }
  ],
  "positions": [
    {
      "symbol": "NIFTY2660922400PE",
      "quantity": -12090,
      "avg": 0.68,
      "ltp": 0.55,
      "pnl": 1560.0,
      "unrealised": 1560.0,
      "realised": 0.0,
      "buy_qty": 0,
      "sell_qty": 12090,
      "product": "NRML"
    },
    {
      "symbol": "NIFTY2660924000CE",
      "quantity": -12285,
      "avg": 0.67,
      "ltp": 0.8,
      "pnl": -1579.5,
      "unrealised": -1579.5,
      "realised": 0.0,
      "buy_qty": 0,
      "sell_qty": 12285,
      "product": "NRML"
    },
    {
      "symbol": "GOLDBEES",
      "quantity": 302,
      "avg": 125.51,
      "ltp": 125.89,
      "pnl": 114.76,
      "unrealised": 114.76,
      "realised": 0.0,
      "buy_qty": 302,
      "sell_qty": 0,
      "product": "CNC"
    },
    {
      "symbol": "LIQUIDCASE",
      "quantity": -271,
      "avg": 114.44,
      "ltp": 114.46,
      "pnl": -4.74,
      "unrealised": -4.74,
      "realised": 0.0,
      "buy_qty": 0,
      "sell_qty": 271,
      "product": "CNC"
    }
  ],
  "williams_r": [
    {
      "symbol": "GOLDBEES",
      "ltp": 125.88,
      "change_pct": 1.39,
      "williams_r": -75.3,
      "is_held": true,
      "avg_price": 126.01,
      "strategy": "active"
    },
    {
      "symbol": "SILVERBEES",
      "ltp": 232.97,
      "change_pct": 2.21,
      "williams_r": -75.37,
      "is_held": true,
      "avg_price": 244.4,
      "strategy": "active"
    },
    {
      "symbol": "JUNIORBEES",
      "ltp": 752.0,
      "change_pct": 0.96,
      "williams_r": -63.69,
      "is_held": true,
      "avg_price": 748.0,
      "strategy": "active"
    },
    {
      "symbol": "MINDSPACE-RR",
      "ltp": 464.02,
      "change_pct": 0.89,
      "williams_r": -36.98,
      "is_held": true,
      "avg_price": 458.0,
      "strategy": "active"
    },
    {
      "symbol": "EMBASSY-RR",
      "ltp": 429.54,
      "change_pct": 0.8,
      "williams_r": -68.95,
      "is_held": true,
      "avg_price": 426.36,
      "strategy": "active"
    },
    {
      "symbol": "BANKBEES",
      "ltp": 564.4,
      "change_pct": 1.02,
      "williams_r": -34.27,
      "is_held": true,
      "avg_price": 550.41,
      "strategy": "active"
    },
    {
      "symbol": "MID150BEES",
      "ltp": 228.5,
      "change_pct": 0.73,
      "williams_r": -75.38,
      "is_held": true,
      "avg_price": 227.65,
      "strategy": "bnh"
    }
  ],
  "signals": [],
  "orders": [
    {
      "order_id": "260609150357025",
      "tradingsymbol": "LIQUIDCASE",
      "transaction_type": "SELL",
      "quantity": 67,
      "filled_quantity": 67,
      "average_price": 114.44,
      "price": 0,
      "status": "COMPLETE",
      "order_timestamp": "2026-06-09 09:48:08"
    },
    {
      "order_id": "260609150441731",
      "tradingsymbol": "LIQUIDCASE",
      "transaction_type": "SELL",
      "quantity": 68,
      "filled_quantity": 68,
      "average_price": 114.44,
      "price": 0,
      "status": "COMPLETE",
      "order_timestamp": "2026-06-09 10:00:52"
    },
    {
      "order_id": "260609150502605",
      "tradingsymbol": "LIQUIDCASE",
      "transaction_type": "SELL",
      "quantity": 68,
      "filled_quantity": 68,
      "average_price": 114.44,
      "price": 0,
      "status": "COMPLETE",
      "order_timestamp": "2026-06-09 10:11:59"
    },
    {
      "order_id": "260609150611503",
      "tradingsymbol": "LIQUIDCASE",
      "transaction_type": "SELL",
      "quantity": 68,
      "filled_quantity": 68,
      "average_price": 114.45,
      "price": 0,
      "status": "COMPLETE",
      "order_timestamp": "2026-06-09 10:37:45"
    },
    {
      "order_id": "260609150651537",
      "tradingsymbol": "GOLDBEES",
      "transaction_type": "BUY",
      "quantity": 302,
      "filled_quantity": 302,
      "average_price": 125.51,
      "price": 125.51,
      "status": "COMPLETE",
      "order_timestamp": "2026-06-09 10:49:09"
    }
  ],
  "indices": {
    "NIFTY 50": {
      "ltp": 23176.8,
      "prev_close": 23123.0,
      "change": 53.8,
      "change_pct": 0.23,
      "open": 23259.05,
      "high": 23259.45,
      "low": 23104.45
    },
    "INDIA VIX": {
      "ltp": 16.04,
      "prev_close": 17.03,
      "change": -0.99,
      "change_pct": -5.81,
      "open": 17.03,
      "high": 17.03,
      "low": 15.8
    }
  },
  "available_cash": 10084.0,
  "available_margin": 288077.48,
  "available_margin_note": null
}