{
  "account": "PS5673",
  "timestamp": "2026-06-08 10:56:59 IST",
  "bot_running": true,
  "total_value": 9121740.59,
  "today_pnl": -8660.8,
  "today_pnl_pct": -0.09,
  "liquidcase": {
    "quantity": 76358,
    "free_quantity": 9040,
    "price": 114.43,
    "value": 8737645.94,
    "pct": 95.79
  },
  "slots": {
    "total": 5,
    "used": 5,
    "available": 0,
    "active_etfs": [
      "MON100",
      "GOLDBEES",
      "SILVERBEES",
      "JUNIORBEES",
      "MINDSPACE-RR",
      "EMBASSY-RR",
      "BANKBEES"
    ],
    "bnh_symbols": [
      "MID150BEES"
    ],
    "bnh_held": 1
  },
  "holdings": [
    {
      "symbol": "BANKBEES",
      "quantity": 34,
      "avg": 550.41,
      "ltp": 560.13,
      "value": 19044.42,
      "pnl": -100.3,
      "pnl_pct": -0.52,
      "strategy": "active",
      "buys_today": 0,
      "max_slots": 5
    },
    {
      "symbol": "GOLDBEES",
      "quantity": 547,
      "avg": 127.75,
      "ltp": 124.5,
      "value": 68101.5,
      "pnl": -1794.16,
      "pnl_pct": -2.57,
      "strategy": "active",
      "buys_today": 0,
      "max_slots": 5
    },
    {
      "symbol": "JUNIORBEES",
      "quantity": 26,
      "avg": 748.0,
      "ltp": 752.54,
      "value": 19566.04,
      "pnl": -135.72,
      "pnl_pct": -0.69,
      "strategy": "active",
      "buys_today": 0,
      "max_slots": 5
    },
    {
      "symbol": "MID150BEES",
      "quantity": 721,
      "avg": 227.48,
      "ltp": 228.88,
      "value": 165022.48,
      "pnl": -807.52,
      "pnl_pct": -0.49,
      "strategy": "bnh",
      "buys_today": null,
      "max_slots": 5
    },
    {
      "symbol": "MINDSPACE-RR",
      "quantity": 43,
      "avg": 458.0,
      "ltp": 459.99,
      "value": 19779.57,
      "pnl": 2.58,
      "pnl_pct": 0.01,
      "strategy": "active",
      "buys_today": 0,
      "max_slots": 5
    },
    {
      "symbol": "SILVERBEES",
      "quantity": 404,
      "avg": 247.45,
      "ltp": 229.16,
      "value": 92580.64,
      "pnl": -5825.68,
      "pnl_pct": -5.92,
      "strategy": "active",
      "buys_today": 0,
      "max_slots": 5
    }
  ],
  "positions": [
    {
      "symbol": "NIFTY2660921600PE",
      "quantity": -21060,
      "avg": 2.21,
      "ltp": 0.95,
      "pnl": 26500.49,
      "unrealised": 26500.49,
      "realised": 0.0,
      "buy_qty": 0,
      "sell_qty": 21060,
      "product": "NRML"
    },
    {
      "symbol": "NIFTY2660925200CE",
      "quantity": -20085,
      "avg": 1.57,
      "ltp": 0.85,
      "pnl": 14371.5,
      "unrealised": 14371.5,
      "realised": 0.0,
      "buy_qty": 0,
      "sell_qty": 20085,
      "product": "NRML"
    },
    {
      "symbol": "GOLDBEES",
      "quantity": 243,
      "avg": 124.81,
      "ltp": 124.53,
      "pnl": -67.54,
      "unrealised": -67.54,
      "realised": 0.0,
      "buy_qty": 243,
      "sell_qty": 0,
      "product": "CNC"
    },
    {
      "symbol": "LIQUIDCASE",
      "quantity": -2793,
      "avg": 114.43,
      "ltp": 114.43,
      "pnl": -0.04,
      "unrealised": -0.04,
      "realised": 0.0,
      "buy_qty": 0,
      "sell_qty": 2793,
      "product": "CNC"
    },
    {
      "symbol": "MID150BEES",
      "quantity": 569,
      "avg": 227.88,
      "ltp": 228.55,
      "pnl": 378.79,
      "unrealised": 378.79,
      "realised": 0.0,
      "buy_qty": 569,
      "sell_qty": 0,
      "product": "CNC"
    },
    {
      "symbol": "NIFTYBEES",
      "quantity": 227,
      "avg": 262.7,
      "ltp": 263.5,
      "pnl": 181.6,
      "unrealised": 181.6,
      "realised": 0.0,
      "buy_qty": 227,
      "sell_qty": 0,
      "product": "CNC"
    },
    {
      "symbol": "SILVERBEES",
      "quantity": 86,
      "avg": 230.07,
      "ltp": 229.3,
      "pnl": -66.22,
      "unrealised": -66.22,
      "realised": 0.0,
      "buy_qty": 86,
      "sell_qty": 0,
      "product": "CNC"
    }
  ],
  "williams_r": [
    {
      "symbol": "MON100",
      "ltp": 339.9,
      "change_pct": -0.77,
      "williams_r": -9.81,
      "is_held": false,
      "avg_price": null,
      "strategy": "active"
    },
    {
      "symbol": "GOLDBEES",
      "ltp": 124.5,
      "change_pct": -2.57,
      "williams_r": -90.32,
      "is_held": true,
      "avg_price": 126.84,
      "strategy": "active"
    },
    {
      "symbol": "SILVERBEES",
      "ltp": 229.16,
      "change_pct": -5.92,
      "williams_r": -96.61,
      "is_held": true,
      "avg_price": 244.4,
      "strategy": "active"
    },
    {
      "symbol": "JUNIORBEES",
      "ltp": 752.54,
      "change_pct": -0.69,
      "williams_r": -62.5,
      "is_held": true,
      "avg_price": 748.0,
      "strategy": "active"
    },
    {
      "symbol": "MINDSPACE-RR",
      "ltp": 459.99,
      "change_pct": 0.01,
      "williams_r": -80.18,
      "is_held": true,
      "avg_price": 458.0,
      "strategy": "active"
    },
    {
      "symbol": "EMBASSY-RR",
      "ltp": 426.55,
      "change_pct": -0.39,
      "williams_r": -76.76,
      "is_held": false,
      "avg_price": null,
      "strategy": "active"
    },
    {
      "symbol": "BANKBEES",
      "ltp": 560.13,
      "change_pct": -0.52,
      "williams_r": -49.54,
      "is_held": true,
      "avg_price": 550.41,
      "strategy": "active"
    },
    {
      "symbol": "MID150BEES",
      "ltp": 228.88,
      "change_pct": -0.49,
      "williams_r": -72.36,
      "is_held": true,
      "avg_price": 227.66,
      "strategy": "bnh"
    }
  ],
  "signals": [
    {
      "type": "BUY",
      "symbol": "EMBASSY-RR",
      "reason": "W%R -76.8 \u2264 -75.0",
      "ltp": 426.55,
      "williams_r": -76.76
    }
  ],
  "orders": [],
  "indices": {
    "NIFTY 50": {
      "ltp": 23197.75,
      "prev_close": 23366.7,
      "change": -168.95,
      "change_pct": -0.72,
      "open": 23080.7,
      "high": 23223.45,
      "low": 23070.15
    },
    "INDIA VIX": {
      "ltp": 16.94,
      "prev_close": 15.79,
      "change": 1.15,
      "change_pct": 7.28,
      "open": 15.79,
      "high": 18.44,
      "low": 15.79
    }
  },
  "available_cash": null,
  "available_margin": null,
  "available_margin_note": "HTTP 403"
}