{
  "account": "PS5673",
  "timestamp": "2026-06-09 09:24:04 IST",
  "bot_running": true,
  "total_value": 9369618.88,
  "today_pnl": 6158.12,
  "today_pnl_pct": 0.07,
  "liquidcase": {
    "quantity": 76184,
    "free_quantity": 8866,
    "price": 114.44,
    "value": 8718496.96,
    "pct": 93.05
  },
  "slots": {
    "total": 5,
    "used": 6,
    "available": 0,
    "active_etfs": [
      "MON100",
      "GOLDBEES",
      "SILVERBEES",
      "JUNIORBEES",
      "MINDSPACE-RR",
      "EMBASSY-RR",
      "BANKBEES"
    ],
    "bnh_symbols": [
      "MID150BEES"
    ],
    "bnh_held": 1
  },
  "holdings": [
    {
      "symbol": "BANKBEES",
      "quantity": 34,
      "avg": 550.41,
      "ltp": 564.19,
      "value": 19182.46,
      "pnl": 186.32,
      "pnl_pct": 0.98,
      "strategy": "active",
      "buys_today": 0,
      "max_slots": 5
    },
    {
      "symbol": "EMBASSY-RR",
      "quantity": 70,
      "avg": 426.36,
      "ltp": 427.18,
      "value": 29902.6,
      "pnl": 74.9,
      "pnl_pct": 0.25,
      "strategy": "active",
      "buys_today": 0,
      "max_slots": 5
    },
    {
      "symbol": "GOLDBEES",
      "quantity": 1111,
      "avg": 126.14,
      "ltp": 125.7,
      "value": 139652.7,
      "pnl": 1710.94,
      "pnl_pct": 1.24,
      "strategy": "active",
      "buys_today": 0,
      "max_slots": 5
    },
    {
      "symbol": "JUNIORBEES",
      "quantity": 26,
      "avg": 748.0,
      "ltp": 749.76,
      "value": 19493.76,
      "pnl": 126.88,
      "pnl_pct": 0.66,
      "strategy": "active",
      "buys_today": 0,
      "max_slots": 5
    },
    {
      "symbol": "MID150BEES",
      "quantity": 1355,
      "avg": 227.65,
      "ltp": 228.49,
      "value": 309603.95,
      "pnl": 2235.75,
      "pnl_pct": 0.73,
      "strategy": "bnh",
      "buys_today": null,
      "max_slots": 5
    },
    {
      "symbol": "MINDSPACE-RR",
      "quantity": 43,
      "avg": 458.0,
      "ltp": 460.75,
      "value": 19812.25,
      "pnl": 34.83,
      "pnl_pct": 0.18,
      "strategy": "active",
      "buys_today": 0,
      "max_slots": 5
    },
    {
      "symbol": "SILVERBEES",
      "quantity": 490,
      "avg": 244.4,
      "ltp": 231.58,
      "value": 113474.2,
      "pnl": 1788.5,
      "pnl_pct": 1.6,
      "strategy": "active",
      "buys_today": 0,
      "max_slots": 5
    }
  ],
  "positions": [
    {
      "symbol": "NIFTY2660921600PE",
      "quantity": -21060,
      "avg": 2.21,
      "ltp": 0.6,
      "pnl": 33871.49,
      "unrealised": 33871.49,
      "realised": 0.0,
      "buy_qty": 0,
      "sell_qty": 21060,
      "product": "NRML"
    },
    {
      "symbol": "NIFTY2660925200CE",
      "quantity": -20085,
      "avg": 1.57,
      "ltp": 0.7,
      "pnl": 17384.25,
      "unrealised": 17384.25,
      "realised": 0.0,
      "buy_qty": 0,
      "sell_qty": 20085,
      "product": "NRML"
    }
  ],
  "williams_r": [
    {
      "symbol": "MON100",
      "ltp": 321.98,
      "change_pct": -2.69,
      "williams_r": -76.19,
      "is_held": false,
      "avg_price": null,
      "strategy": "active"
    },
    {
      "symbol": "GOLDBEES",
      "ltp": 125.7,
      "change_pct": 1.24,
      "williams_r": -77.26,
      "is_held": true,
      "avg_price": 126.14,
      "strategy": "active"
    },
    {
      "symbol": "SILVERBEES",
      "ltp": 231.58,
      "change_pct": 1.6,
      "williams_r": -79.78,
      "is_held": true,
      "avg_price": 244.4,
      "strategy": "active"
    },
    {
      "symbol": "JUNIORBEES",
      "ltp": 749.76,
      "change_pct": 0.66,
      "williams_r": -68.63,
      "is_held": true,
      "avg_price": 748.0,
      "strategy": "active"
    },
    {
      "symbol": "MINDSPACE-RR",
      "ltp": 460.75,
      "change_pct": 0.18,
      "williams_r": -66.55,
      "is_held": true,
      "avg_price": 458.0,
      "strategy": "active"
    },
    {
      "symbol": "EMBASSY-RR",
      "ltp": 427.18,
      "change_pct": 0.25,
      "williams_r": -85.45,
      "is_held": true,
      "avg_price": 426.36,
      "strategy": "active"
    },
    {
      "symbol": "BANKBEES",
      "ltp": 564.19,
      "change_pct": 0.98,
      "williams_r": -35.03,
      "is_held": true,
      "avg_price": 550.41,
      "strategy": "active"
    },
    {
      "symbol": "MID150BEES",
      "ltp": 228.49,
      "change_pct": 0.73,
      "williams_r": -75.46,
      "is_held": true,
      "avg_price": 227.65,
      "strategy": "bnh"
    }
  ],
  "signals": [
    {
      "type": "BUY",
      "symbol": "MON100",
      "reason": "W%R -76.2 \u2264 -75.0",
      "ltp": 321.98,
      "williams_r": -76.19
    }
  ],
  "orders": [],
  "indices": {
    "NIFTY 50": {
      "ltp": 23236.3,
      "prev_close": 23123.0,
      "change": 113.3,
      "change_pct": 0.49,
      "open": 23259.05,
      "high": 23259.45,
      "low": 23194.9
    },
    "INDIA VIX": {
      "ltp": 16.21,
      "prev_close": 17.03,
      "change": -0.82,
      "change_pct": -4.82,
      "open": 17.03,
      "high": 17.03,
      "low": 15.83
    }
  },
  "available_cash": null,
  "available_margin": null,
  "available_margin_note": "HTTP 403"
}