{
  "account": "PS5673",
  "timestamp": "2026-06-11 13:47:13 IST",
  "bot_running": true,
  "total_value": 9359161.96,
  "today_pnl": -3338.05,
  "today_pnl_pct": -0.04,
  "liquidcase": {
    "quantity": 74398,
    "free_quantity": 7080,
    "price": 114.48,
    "value": 8517083.04,
    "pct": 91.0
  },
  "slots": {
    "total": 7,
    "used": 5,
    "available": 2,
    "active_etfs": [
      "GOLDBEES",
      "SILVERBEES",
      "JUNIORBEES",
      "MINDSPACE-RR",
      "EMBASSY-RR",
      "BANKBEES"
    ],
    "bnh_symbols": [
      "MID150BEES"
    ],
    "bnh_held": 1
  },
  "holdings": [
    {
      "symbol": "EMBASSY-RR",
      "quantity": 70,
      "avg": 426.36,
      "ltp": 432.89,
      "value": 30302.3,
      "pnl": 235.2,
      "pnl_pct": 0.78,
      "unrealised_pnl": 471.1,
      "unrealised_pnl_pct": 1.58,
      "strategy": "active",
      "buys_today": 1,
      "max_slots": 7
    },
    {
      "symbol": "GOLDBEES",
      "quantity": 2082,
      "avg": 124.77,
      "ltp": 119.64,
      "value": 249090.48,
      "pnl": -3143.82,
      "pnl_pct": -1.25,
      "unrealised_pnl": -10556.2,
      "unrealised_pnl_pct": -4.06,
      "strategy": "active",
      "buys_today": 1,
      "max_slots": 7
    },
    {
      "symbol": "JUNIORBEES",
      "quantity": 26,
      "avg": 748.0,
      "ltp": 739.0,
      "value": 19214.0,
      "pnl": -198.12,
      "pnl_pct": -1.02,
      "unrealised_pnl": -242.58,
      "unrealised_pnl_pct": -1.25,
      "strategy": "active",
      "buys_today": 1,
      "max_slots": 7
    },
    {
      "symbol": "MID150BEES",
      "quantity": 1486,
      "avg": 227.69,
      "ltp": 224.89,
      "value": 334186.54,
      "pnl": -1694.04,
      "pnl_pct": -0.5,
      "unrealised_pnl": -4081.45,
      "unrealised_pnl_pct": -1.21,
      "strategy": "bnh",
      "buys_today": 1,
      "max_slots": 7
    },
    {
      "symbol": "MINDSPACE-RR",
      "quantity": 43,
      "avg": 458.0,
      "ltp": 460.88,
      "value": 19817.84,
      "pnl": -62.35,
      "pnl_pct": -0.31,
      "unrealised_pnl": 128.14,
      "unrealised_pnl_pct": 0.65,
      "strategy": "active",
      "buys_today": 1,
      "max_slots": 7
    },
    {
      "symbol": "SILVERBEES",
      "quantity": 852,
      "avg": 234.71,
      "ltp": 222.38,
      "value": 189467.76,
      "pnl": 1525.08,
      "pnl_pct": 0.81,
      "unrealised_pnl": -10505.85,
      "unrealised_pnl_pct": -5.25,
      "strategy": "active",
      "buys_today": 1,
      "max_slots": 7
    }
  ],
  "positions": [
    {
      "symbol": "NIFTY2661621500PE",
      "quantity": -21060,
      "avg": 2.29,
      "ltp": 1.85,
      "pnl": 9213.75,
      "unrealised": 9213.75,
      "realised": 0.0,
      "buy_qty": 0,
      "sell_qty": 21060,
      "product": "NRML"
    },
    {
      "symbol": "NIFTY2661625000CE",
      "quantity": -21060,
      "avg": 1.15,
      "ltp": 0.85,
      "pnl": 6230.24,
      "unrealised": 6230.24,
      "realised": 0.0,
      "buy_qty": 0,
      "sell_qty": 21060,
      "product": "NRML"
    },
    {
      "symbol": "JUNIORBEES",
      "quantity": 27,
      "avg": 740.1,
      "ltp": 739.66,
      "pnl": -11.88,
      "unrealised": -11.88,
      "realised": 0.0,
      "buy_qty": 27,
      "sell_qty": 0,
      "product": "CNC"
    },
    {
      "symbol": "MID150BEES",
      "quantity": 88,
      "avg": 225.4,
      "ltp": 225.01,
      "pnl": -34.32,
      "unrealised": -34.32,
      "realised": 0.0,
      "buy_qty": 88,
      "sell_qty": 0,
      "product": "CNC"
    }
  ],
  "williams_r": [
    {
      "symbol": "GOLDBEES",
      "ltp": 119.64,
      "change_pct": -1.25,
      "williams_r": -64.87,
      "is_held": true,
      "avg_price": 124.77,
      "strategy": "active"
    },
    {
      "symbol": "SILVERBEES",
      "ltp": 222.38,
      "change_pct": 0.81,
      "williams_r": -91.58,
      "is_held": true,
      "avg_price": 234.71,
      "strategy": "active"
    },
    {
      "symbol": "JUNIORBEES",
      "ltp": 739.0,
      "change_pct": -1.02,
      "williams_r": -97.67,
      "is_held": true,
      "avg_price": 743.98,
      "strategy": "active"
    },
    {
      "symbol": "MINDSPACE-RR",
      "ltp": 460.88,
      "change_pct": -0.31,
      "williams_r": -64.17,
      "is_held": true,
      "avg_price": 458.0,
      "strategy": "active"
    },
    {
      "symbol": "EMBASSY-RR",
      "ltp": 432.89,
      "change_pct": 0.78,
      "williams_r": -45.52,
      "is_held": true,
      "avg_price": 426.36,
      "strategy": "active"
    },
    {
      "symbol": "BANKBEES",
      "ltp": 569.49,
      "change_pct": 0.26,
      "williams_r": -17.41,
      "is_held": false,
      "avg_price": null,
      "strategy": "active"
    },
    {
      "symbol": "MID150BEES",
      "ltp": 224.89,
      "change_pct": -0.5,
      "williams_r": -89.73,
      "is_held": true,
      "avg_price": 227.56,
      "strategy": "bnh"
    }
  ],
  "signals": [],
  "orders": [
    {
      "order_id": "260611150093321",
      "tradingsymbol": "JUNIORBEES",
      "transaction_type": "BUY",
      "quantity": 27,
      "filled_quantity": 27,
      "average_price": 740.1,
      "price": 740.1,
      "status": "COMPLETE",
      "order_timestamp": "2026-06-11 09:16:49"
    },
    {
      "order_id": "260611150176064",
      "tradingsymbol": "MID150BEES",
      "transaction_type": "BUY",
      "quantity": 88,
      "filled_quantity": 88,
      "average_price": 225.4,
      "price": 225.4,
      "status": "COMPLETE",
      "order_timestamp": "2026-06-11 09:22:26"
    }
  ],
  "indices": {
    "NIFTY 50": {
      "ltp": 23237.65,
      "prev_close": 23214.95,
      "change": 22.7,
      "change_pct": 0.1,
      "open": 23104.4,
      "high": 23327.45,
      "low": 23072.05
    },
    "INDIA VIX": {
      "ltp": 15.6,
      "prev_close": 15.63,
      "change": -0.03,
      "change_pct": -0.19,
      "open": 15.63,
      "high": 15.95,
      "low": 15.12
    }
  },
  "mf_holdings": [],
  "mf_summary": {},
  "available_cash": 41765.7,
  "available_margin": 1549305.64,
  "available_margin_note": null
}