{
  "account": "PS5673",
  "timestamp": "2026-06-08 12:42:22 IST",
  "bot_running": true,
  "total_value": 9121841.59,
  "today_pnl": -9323.38,
  "today_pnl_pct": -0.1,
  "liquidcase": {
    "quantity": 76358,
    "free_quantity": 9040,
    "price": 114.44,
    "value": 8738409.52,
    "pct": 95.8
  },
  "slots": {
    "total": 5,
    "used": 5,
    "available": 0,
    "active_etfs": [
      "MON100",
      "GOLDBEES",
      "SILVERBEES",
      "JUNIORBEES",
      "MINDSPACE-RR",
      "EMBASSY-RR",
      "BANKBEES"
    ],
    "bnh_symbols": [
      "MID150BEES"
    ],
    "bnh_held": 1
  },
  "holdings": [
    {
      "symbol": "BANKBEES",
      "quantity": 34,
      "avg": 550.41,
      "ltp": 560.87,
      "value": 19069.58,
      "pnl": -75.14,
      "pnl_pct": -0.39,
      "strategy": "active",
      "buys_today": 0,
      "max_slots": 5
    },
    {
      "symbol": "GOLDBEES",
      "quantity": 547,
      "avg": 127.75,
      "ltp": 124.29,
      "value": 67986.63,
      "pnl": -1909.03,
      "pnl_pct": -2.73,
      "strategy": "active",
      "buys_today": 0,
      "max_slots": 5
    },
    {
      "symbol": "JUNIORBEES",
      "quantity": 26,
      "avg": 748.0,
      "ltp": 752.49,
      "value": 19564.74,
      "pnl": -137.02,
      "pnl_pct": -0.7,
      "strategy": "active",
      "buys_today": 0,
      "max_slots": 5
    },
    {
      "symbol": "MID150BEES",
      "quantity": 721,
      "avg": 227.48,
      "ltp": 229.0,
      "value": 165109.0,
      "pnl": -721.0,
      "pnl_pct": -0.43,
      "strategy": "bnh",
      "buys_today": null,
      "max_slots": 5
    },
    {
      "symbol": "MINDSPACE-RR",
      "quantity": 43,
      "avg": 458.0,
      "ltp": 460.0,
      "value": 19780.0,
      "pnl": 3.01,
      "pnl_pct": 0.02,
      "strategy": "active",
      "buys_today": 0,
      "max_slots": 5
    },
    {
      "symbol": "SILVERBEES",
      "quantity": 404,
      "avg": 247.45,
      "ltp": 227.53,
      "value": 91922.12,
      "pnl": -6484.2,
      "pnl_pct": -6.59,
      "strategy": "active",
      "buys_today": 0,
      "max_slots": 5
    }
  ],
  "positions": [
    {
      "symbol": "NIFTY2660921600PE",
      "quantity": -21060,
      "avg": 2.21,
      "ltp": 0.95,
      "pnl": 26500.49,
      "unrealised": 26500.49,
      "realised": 0.0,
      "buy_qty": 0,
      "sell_qty": 21060,
      "product": "NRML"
    },
    {
      "symbol": "NIFTY2660925200CE",
      "quantity": -20085,
      "avg": 1.57,
      "ltp": 0.7,
      "pnl": 17384.25,
      "unrealised": 17384.25,
      "realised": 0.0,
      "buy_qty": 0,
      "sell_qty": 20085,
      "product": "NRML"
    },
    {
      "symbol": "EMBASSY-RR",
      "quantity": 70,
      "avg": 426.36,
      "ltp": 427.28,
      "pnl": 64.4,
      "unrealised": 64.4,
      "realised": 0.0,
      "buy_qty": 70,
      "sell_qty": 0,
      "product": "CNC"
    },
    {
      "symbol": "GOLDBEES",
      "quantity": 564,
      "avg": 124.58,
      "ltp": 124.25,
      "pnl": -186.94,
      "unrealised": -186.94,
      "realised": 0.0,
      "buy_qty": 564,
      "sell_qty": 0,
      "product": "CNC"
    },
    {
      "symbol": "LIQUIDCASE",
      "quantity": -2793,
      "avg": 114.43,
      "ltp": 114.44,
      "pnl": -27.97,
      "unrealised": -27.97,
      "realised": 0.0,
      "buy_qty": 0,
      "sell_qty": 2793,
      "product": "CNC"
    },
    {
      "symbol": "MID150BEES",
      "quantity": 569,
      "avg": 227.88,
      "ltp": 229.04,
      "pnl": 657.6,
      "unrealised": 657.6,
      "realised": 0.0,
      "buy_qty": 569,
      "sell_qty": 0,
      "product": "CNC"
    },
    {
      "symbol": "NIFTYBEES",
      "quantity": 227,
      "avg": 262.7,
      "ltp": 263.75,
      "pnl": 238.35,
      "unrealised": 238.35,
      "realised": 0.0,
      "buy_qty": 227,
      "sell_qty": 0,
      "product": "CNC"
    },
    {
      "symbol": "SILVERBEES",
      "quantity": 86,
      "avg": 230.07,
      "ltp": 227.38,
      "pnl": -231.34,
      "unrealised": -231.34,
      "realised": 0.0,
      "buy_qty": 86,
      "sell_qty": 0,
      "product": "CNC"
    }
  ],
  "williams_r": [
    {
      "symbol": "MON100",
      "ltp": 337.37,
      "change_pct": -1.51,
      "williams_r": -19.19,
      "is_held": false,
      "avg_price": null,
      "strategy": "active"
    },
    {
      "symbol": "GOLDBEES",
      "ltp": 124.29,
      "change_pct": -2.73,
      "williams_r": -92.6,
      "is_held": true,
      "avg_price": 126.14,
      "strategy": "active"
    },
    {
      "symbol": "SILVERBEES",
      "ltp": 227.53,
      "change_pct": -6.59,
      "williams_r": -92.75,
      "is_held": true,
      "avg_price": 244.4,
      "strategy": "active"
    },
    {
      "symbol": "JUNIORBEES",
      "ltp": 752.49,
      "change_pct": -0.7,
      "williams_r": -62.61,
      "is_held": true,
      "avg_price": 748.0,
      "strategy": "active"
    },
    {
      "symbol": "MINDSPACE-RR",
      "ltp": 460.0,
      "change_pct": 0.02,
      "williams_r": -80.11,
      "is_held": true,
      "avg_price": 458.0,
      "strategy": "active"
    },
    {
      "symbol": "EMBASSY-RR",
      "ltp": 427.06,
      "change_pct": -0.27,
      "williams_r": -73.72,
      "is_held": false,
      "avg_price": null,
      "strategy": "active"
    },
    {
      "symbol": "BANKBEES",
      "ltp": 560.87,
      "change_pct": -0.39,
      "williams_r": -46.89,
      "is_held": true,
      "avg_price": 550.41,
      "strategy": "active"
    },
    {
      "symbol": "MID150BEES",
      "ltp": 229.0,
      "change_pct": -0.43,
      "williams_r": -71.41,
      "is_held": true,
      "avg_price": 227.66,
      "strategy": "bnh"
    }
  ],
  "signals": [],
  "orders": [
    {
      "order_id": "260608150087185",
      "tradingsymbol": "LIQUIDCASE",
      "transaction_type": "SELL",
      "quantity": 1747,
      "filled_quantity": 1747,
      "average_price": 114.43,
      "price": 114.43,
      "status": "COMPLETE",
      "order_timestamp": "2026-06-08 09:16:03"
    },
    {
      "order_id": "260608150173277",
      "tradingsymbol": "MID150BEES",
      "transaction_type": "BUY",
      "quantity": 307,
      "filled_quantity": 0,
      "average_price": 0,
      "price": 227.91,
      "status": "REJECTED",
      "order_timestamp": "2026-06-08 09:21:28"
    },
    {
      "order_id": "260608150175028",
      "tradingsymbol": "MID150BEES",
      "transaction_type": "BUY",
      "quantity": 218,
      "filled_quantity": 218,
      "average_price": 228.02,
      "price": 228.02,
      "status": "COMPLETE",
      "order_timestamp": "2026-06-08 09:24:42"
    },
    {
      "order_id": "260608150161920",
      "tradingsymbol": "MID150BEES",
      "transaction_type": "BUY",
      "quantity": 351,
      "filled_quantity": 351,
      "average_price": 227.8,
      "price": 227.8,
      "status": "COMPLETE",
      "order_timestamp": "2026-06-08 09:20:42"
    },
    {
      "order_id": "260608150317305",
      "tradingsymbol": "LIQUIDCASE",
      "transaction_type": "SELL",
      "quantity": 524,
      "filled_quantity": 524,
      "average_price": 114.43,
      "price": 114.43,
      "status": "COMPLETE",
      "order_timestamp": "2026-06-08 09:33:49"
    },
    {
      "order_id": "260608150321435",
      "tradingsymbol": "GOLDBEES",
      "transaction_type": "BUY",
      "quantity": 240,
      "filled_quantity": 240,
      "average_price": 124.81,
      "price": 124.81,
      "status": "COMPLETE",
      "order_timestamp": "2026-06-08 09:34:18"
    },
    {
      "order_id": "260608150325136",
      "tradingsymbol": "SILVERBEES",
      "transaction_type": "BUY",
      "quantity": 86,
      "filled_quantity": 86,
      "average_price": 230.07,
      "price": 230.07,
      "status": "COMPLETE",
      "order_timestamp": "2026-06-08 09:34:44"
    },
    {
      "order_id": "260608150466682",
      "tradingsymbol": "LIQUIDCASE",
      "transaction_type": "SELL",
      "quantity": 2,
      "filled_quantity": 2,
      "average_price": 114.42,
      "price": 0,
      "status": "COMPLETE",
      "order_timestamp": "2026-06-08 09:53:31"
    },
    {
      "order_id": "260608150471376",
      "tradingsymbol": "LIQUIDCASE",
      "transaction_type": "SELL",
      "quantity": 2,
      "filled_quantity": 2,
      "average_price": 114.42,
      "price": 0,
      "status": "COMPLETE",
      "order_timestamp": "2026-06-08 09:54:19"
    },
    {
      "order_id": "260608150476264",
      "tradingsymbol": "LIQUIDCASE",
      "transaction_type": "SELL",
      "quantity": 2,
      "filled_quantity": 2,
      "average_price": 114.43,
      "price": 0,
      "status": "COMPLETE",
      "order_timestamp": "2026-06-08 09:55:07"
    },
    {
      "order_id": "260608150476540",
      "tradingsymbol": "GOLDBEES",
      "transaction_type": "BUY",
      "quantity": 1,
      "filled_quantity": 1,
      "average_price": 124.69,
      "price": 124.69,
      "status": "COMPLETE",
      "order_timestamp": "2026-06-08 09:55:10"
    },
    {
      "order_id": "260608150532231",
      "tradingsymbol": "LIQUIDCASE",
      "transaction_type": "SELL",
      "quantity": 172,
      "filled_quantity": 172,
      "average_price": 114.43,
      "price": 0,
      "status": "COMPLETE",
      "order_timestamp": "2026-06-08 10:04:14"
    },
    {
      "order_id": "260608150471632",
      "tradingsymbol": "GOLDBEES",
      "transaction_type": "BUY",
      "quantity": 1,
      "filled_quantity": 1,
      "average_price": 124.63,
      "price": 124.63,
      "status": "COMPLETE",
      "order_timestamp": "2026-06-08 09:54:22"
    },
    {
      "order_id": "260608150466989",
      "tradingsymbol": "GOLDBEES",
      "transaction_type": "BUY",
      "quantity": 1,
      "filled_quantity": 1,
      "average_price": 124.61,
      "price": 124.61,
      "status": "COMPLETE",
      "order_timestamp": "2026-06-08 09:53:34"
    },
    {
      "order_id": "260608150631075",
      "tradingsymbol": "LIQUIDCASE",
      "transaction_type": "SELL",
      "quantity": 172,
      "filled_quantity": 172,
      "average_price": 114.43,
      "price": 0,
      "status": "COMPLETE",
      "order_timestamp": "2026-06-08 10:27:35"
    },
    {
      "order_id": "260608150650113",
      "tradingsymbol": "LIQUIDCASE",
      "transaction_type": "SELL",
      "quantity": 172,
      "filled_quantity": 172,
      "average_price": 114.43,
      "price": 0,
      "status": "COMPLETE",
      "order_timestamp": "2026-06-08 10:31:53"
    },
    {
      "order_id": "260608150699994",
      "tradingsymbol": "GOLDBEES",
      "transaction_type": "BUY",
      "quantity": 321,
      "filled_quantity": 321,
      "average_price": 124.41,
      "price": 124.41,
      "status": "COMPLETE",
      "order_timestamp": "2026-06-08 10:43:57"
    },
    {
      "order_id": "260608150705651",
      "tradingsymbol": "EMBASSY-RR",
      "transaction_type": "BUY",
      "quantity": 70,
      "filled_quantity": 70,
      "average_price": 426.36,
      "price": 426.36,
      "status": "COMPLETE",
      "order_timestamp": "2026-06-08 10:45:09"
    }
  ],
  "indices": {
    "NIFTY 50": {
      "ltp": 23226.15,
      "prev_close": 23366.7,
      "change": -140.55,
      "change_pct": -0.6,
      "open": 23080.7,
      "high": 23228.05,
      "low": 23070.15
    },
    "INDIA VIX": {
      "ltp": 16.92,
      "prev_close": 15.79,
      "change": 1.13,
      "change_pct": 7.16,
      "open": 15.79,
      "high": 18.44,
      "low": 15.79
    }
  },
  "available_cash": 12385.73,
  "available_margin": 1882380.46,
  "available_margin_note": null
}