{
  "account": "RD1858",
  "timestamp": "2026-06-04 11:46:25 IST",
  "bot_running": true,
  "total_value": 9586071.25,
  "today_pnl": 4558.06,
  "today_pnl_pct": 0.05,
  "liquidcase": {
    "quantity": 78529,
    "price": 114.37,
    "value": 8981361.73,
    "pct": 93.69
  },
  "slots": {
    "total": 5,
    "used": 5,
    "available": 0,
    "active_etfs": [
      "MON100",
      "GOLDBEES",
      "SILVERBEES",
      "JUNIORBEES",
      "MINDSPACE-RR",
      "EMBASSY-RR",
      "BANKBEES"
    ],
    "bnh_symbols": [
      "MID150BEES"
    ],
    "bnh_held": 1
  },
  "holdings": [
    {
      "symbol": "BANKBEES",
      "quantity": 36,
      "avg": 553.2,
      "ltp": 560.66,
      "value": 20183.76,
      "pnl": 268.56,
      "pnl_pct": 1.35,
      "strategy": "active"
    },
    {
      "symbol": "GOLDBEES",
      "quantity": 546,
      "avg": 127.78,
      "ltp": 128.53,
      "value": 70177.38,
      "pnl": 411.01,
      "pnl_pct": 0.59,
      "strategy": "active"
    },
    {
      "symbol": "JUNIORBEES",
      "quantity": 26,
      "avg": 748.0,
      "ltp": 758.65,
      "value": 19724.9,
      "pnl": 276.9,
      "pnl_pct": 1.42,
      "strategy": "active"
    },
    {
      "symbol": "MID150BEES",
      "quantity": 1125,
      "avg": 227.88,
      "ltp": 231.46,
      "value": 260392.5,
      "pnl": 4023.11,
      "pnl_pct": 1.57,
      "strategy": "bnh"
    },
    {
      "symbol": "MINDSPACE-RR",
      "quantity": 316,
      "avg": 458.27,
      "ltp": 460.0,
      "value": 145360.0,
      "pnl": 545.5,
      "pnl_pct": 0.38,
      "strategy": "active"
    },
    {
      "symbol": "SILVERBEES",
      "quantity": 361,
      "avg": 248.86,
      "ltp": 246.18,
      "value": 88870.98,
      "pnl": -967.02,
      "pnl_pct": -1.08,
      "strategy": "active"
    }
  ],
  "williams_r": [
    {
      "symbol": "MON100",
      "ltp": 341.98,
      "change_pct": 0.77,
      "williams_r": 0.0,
      "is_held": false,
      "avg_price": null,
      "strategy": "active"
    },
    {
      "symbol": "GOLDBEES",
      "ltp": 128.53,
      "change_pct": 0.7,
      "williams_r": -79.08,
      "is_held": true,
      "avg_price": 127.78,
      "strategy": "active"
    },
    {
      "symbol": "SILVERBEES",
      "ltp": 246.18,
      "change_pct": -0.25,
      "williams_r": -93.88,
      "is_held": true,
      "avg_price": 248.54,
      "strategy": "active"
    },
    {
      "symbol": "JUNIORBEES",
      "ltp": 758.65,
      "change_pct": 0.65,
      "williams_r": -42.57,
      "is_held": true,
      "avg_price": 748.0,
      "strategy": "active"
    },
    {
      "symbol": "MINDSPACE-RR",
      "ltp": 460.0,
      "change_pct": -0.05,
      "williams_r": -68.75,
      "is_held": true,
      "avg_price": 458.27,
      "strategy": "active"
    },
    {
      "symbol": "EMBASSY-RR",
      "ltp": 429.98,
      "change_pct": -0.45,
      "williams_r": -44.23,
      "is_held": false,
      "avg_price": null,
      "strategy": "active"
    },
    {
      "symbol": "BANKBEES",
      "ltp": 560.66,
      "change_pct": 0.18,
      "williams_r": -47.54,
      "is_held": true,
      "avg_price": 553.2,
      "strategy": "active"
    },
    {
      "symbol": "MID150BEES",
      "ltp": 231.46,
      "change_pct": 0.71,
      "williams_r": -50.74,
      "is_held": true,
      "avg_price": 227.88,
      "strategy": "bnh"
    }
  ],
  "signals": [],
  "orders": [
    {
      "order_id": "260604190042135",
      "tradingsymbol": "SILVERBEES",
      "transaction_type": "BUY",
      "quantity": 41,
      "filled_quantity": 41,
      "average_price": 245.71,
      "price": 245.71,
      "status": "COMPLETE",
      "order_timestamp": "2026-06-04 09:15:11"
    }
  ]
}