{
  "account": "RD1858",
  "timestamp": "2026-06-05 13:50:52 IST",
  "bot_running": true,
  "total_value": 9595866.18,
  "today_pnl": -3748.09,
  "today_pnl_pct": -0.04,
  "liquidcase": {
    "quantity": 78529,
    "price": 114.42,
    "value": 8985288.18,
    "pct": 93.64
  },
  "slots": {
    "total": 5,
    "used": 5,
    "available": 0,
    "active_etfs": [
      "MON100",
      "GOLDBEES",
      "SILVERBEES",
      "JUNIORBEES",
      "MINDSPACE-RR",
      "EMBASSY-RR",
      "BANKBEES"
    ],
    "bnh_symbols": [
      "MID150BEES"
    ],
    "bnh_held": 1
  },
  "holdings": [
    {
      "symbol": "BANKBEES",
      "quantity": 36,
      "avg": 553.2,
      "ltp": 560.25,
      "value": 20169.0,
      "pnl": -36.72,
      "pnl_pct": -0.18,
      "strategy": "active"
    },
    {
      "symbol": "GOLDBEES",
      "quantity": 546,
      "avg": 127.78,
      "ltp": 127.7,
      "value": 69724.2,
      "pnl": -436.8,
      "pnl_pct": -0.62,
      "strategy": "active"
    },
    {
      "symbol": "JUNIORBEES",
      "quantity": 26,
      "avg": 748.0,
      "ltp": 754.86,
      "value": 19626.36,
      "pnl": -31.72,
      "pnl_pct": -0.16,
      "strategy": "active"
    },
    {
      "symbol": "MID150BEES",
      "quantity": 1125,
      "avg": 227.88,
      "ltp": 229.24,
      "value": 257895.0,
      "pnl": -1496.25,
      "pnl_pct": -0.58,
      "strategy": "bnh"
    },
    {
      "symbol": "MINDSPACE-RR",
      "quantity": 316,
      "avg": 458.27,
      "ltp": 459.99,
      "value": 145356.84,
      "pnl": -436.08,
      "pnl_pct": -0.3,
      "strategy": "active"
    },
    {
      "symbol": "SILVERBEES",
      "quantity": 402,
      "avg": 248.54,
      "ltp": 243.3,
      "value": 97806.6,
      "pnl": -1310.52,
      "pnl_pct": -1.32,
      "strategy": "active"
    }
  ],
  "positions": [
    {
      "symbol": "NIFTY2660921600PE",
      "quantity": -17550,
      "avg": 2.13,
      "ltp": 1.1,
      "pnl": 18076.5,
      "unrealised": 18076.5,
      "realised": 0.0,
      "buy_qty": 0,
      "sell_qty": 17550,
      "product": "NRML"
    },
    {
      "symbol": "NIFTY2660925200CE",
      "quantity": -17550,
      "avg": 1.51,
      "ltp": 1.25,
      "pnl": 4650.75,
      "unrealised": 4650.75,
      "realised": 0.0,
      "buy_qty": 0,
      "sell_qty": 17550,
      "product": "NRML"
    }
  ],
  "williams_r": [
    {
      "symbol": "MON100",
      "ltp": 342.55,
      "change_pct": 0.17,
      "williams_r": 0.0,
      "is_held": false,
      "avg_price": null,
      "strategy": "active"
    },
    {
      "symbol": "GOLDBEES",
      "ltp": 127.7,
      "change_pct": -0.62,
      "williams_r": -85.0,
      "is_held": true,
      "avg_price": 127.78,
      "strategy": "active"
    },
    {
      "symbol": "SILVERBEES",
      "ltp": 243.3,
      "change_pct": -1.32,
      "williams_r": -85.94,
      "is_held": true,
      "avg_price": 248.54,
      "strategy": "active"
    },
    {
      "symbol": "JUNIORBEES",
      "ltp": 754.86,
      "change_pct": -0.16,
      "williams_r": -49.83,
      "is_held": true,
      "avg_price": 748.0,
      "strategy": "active"
    },
    {
      "symbol": "MINDSPACE-RR",
      "ltp": 459.99,
      "change_pct": -0.3,
      "williams_r": -68.81,
      "is_held": true,
      "avg_price": 458.27,
      "strategy": "active"
    },
    {
      "symbol": "EMBASSY-RR",
      "ltp": 428.95,
      "change_pct": 0.11,
      "williams_r": -49.06,
      "is_held": false,
      "avg_price": null,
      "strategy": "active"
    },
    {
      "symbol": "BANKBEES",
      "ltp": 560.25,
      "change_pct": -0.18,
      "williams_r": -49.0,
      "is_held": true,
      "avg_price": 553.2,
      "strategy": "active"
    },
    {
      "symbol": "MID150BEES",
      "ltp": 229.24,
      "change_pct": -0.58,
      "williams_r": -67.99,
      "is_held": true,
      "avg_price": 227.88,
      "strategy": "bnh"
    }
  ],
  "signals": [],
  "orders": [],
  "available_cash": 59455.2,
  "available_margin": 2646516.31
}